mgpdf/__about__.py
mgpdf/__init__.py
mgpdf/mgpdf.py
mgpdf/pdfinfo.py
mgpdf/template.tex
mgpdf-0.0.2.dist-info/entry_points.txt
mgpdf-0.0.2.dist-info/LICENSE
mgpdf-0.0.2.dist-info/METADATA
mgpdf-0.0.2.dist-info/WHEEL
mgpdf-0.0.2.dist-info/RECORD
